{
  "0": {
    "members": [
      "GW190403_051519",
      "GW170608",
      "GW170814",
      "GW190503_185404",
      "GW170823",
      "GW190413_052954",
      "GW190413_134308"
    ],
    "T0": 35783583.13713849,
    "T0_days": 414.16184186502886,
    "pairs": [
      {
        "A": "GW190403_051519",
        "B": "GW170608",
        "lam": 0.9525120168793266,
        "t_pred_days": 659.4339394065888
      },
      {
        "A": "GW190403_051519",
        "B": "GW170814",
        "lam": 0.2844037620850852,
        "t_pred_days": 136.2465767216397
      },
      {
        "A": "GW190403_051519",
        "B": "GW190503_185404",
        "lam": 0.5990233222443706,
        "t_pred_days": 339.75354451727
      },
      {
        "A": "GW190403_051519",
        "B": "GW170823",
        "lam": 0.6814412555090215,
        "t_pred_days": 404.5220781578696
      },
      {
        "A": "GW190403_051519",
        "B": "GW190413_052954",
        "lam": 1.461171268059606,
        "t_pred_days": 1371.2923085825335
      },
      {
        "A": "GW190403_051519",
        "B": "GW190413_134308",
        "lam": 1.1740119235108606,
        "t_pred_days": 925.628933980093
      },
      {
        "A": "GW170608",
        "B": "GW170814",
        "lam": 0.6681082547942414,
        "t_pred_days": 393.6790108089267
      },
      {
        "A": "GW170608",
        "B": "GW190503_185404",
        "lam": 0.35348869463495597,
        "t_pred_days": 175.61575681698886
      },
      {
        "A": "GW170608",
        "B": "GW170823",
        "lam": 0.27107076137030517,
        "t_pred_days": 128.95668692877123
      },
      {
        "A": "GW170608",
        "B": "GW190413_052954",
        "lam": 0.5086592511802794,
        "t_pred_days": 274.6141317505374
      },
      {
        "A": "GW170608",
        "B": "GW190413_134308",
        "lam": 0.22149990663153396,
        "t_pred_days": 102.6902407507891
      },
      {
        "A": "GW170814",
        "B": "GW190503_185404",
        "lam": 0.31461956015928544,
        "t_pred_days": 153.13141617824598
      },
      {
        "A": "GW170814",
        "B": "GW170823",
        "lam": 0.39703749342393624,
        "t_pred_days": 201.86732624366215
      },
      {
        "A": "GW170814",
        "B": "GW190413_052954",
        "lam": 1.1767675059745208,
        "t_pred_days": 929.3259292953694
      },
      {
        "A": "GW170814",
        "B": "GW190413_134308",
        "lam": 0.8896081614257754,
        "t_pred_days": 593.9808331010108
      },
      {
        "A": "GW190503_185404",
        "B": "GW170823",
        "lam": 0.08241793326465079,
        "t_pred_days": 35.58045859258462
      },
      {
        "A": "GW190503_185404",
        "B": "GW190413_052954",
        "lam": 0.8621479458152355,
        "t_pred_days": 566.6736641766938
      },
      {
        "A": "GW190503_185404",
        "B": "GW190413_134308",
        "lam": 0.57498860126649,
        "t_pred_days": 321.8494207522
      },
      {
        "A": "GW170823",
        "B": "GW190413_052954",
        "lam": 0.7797300125505846,
        "t_pred_days": 489.07683356203955
      },
      {
        "A": "GW170823",
        "B": "GW190413_134308",
        "lam": 0.49257066800183913,
        "t_pred_days": 263.62136831732266
      },
      {
        "A": "GW190413_052954",
        "B": "GW190413_134308",
        "lam": 0.2871593445487455,
        "t_pred_days": 137.76536411866442
      }
    ]
  },
  "1": {
    "members": [
      "GW190521",
      "GW190519_153544",
      "GW190412",
      "GW190421_213856",
      "GW170104",
      "GW170809",
      "GW151226",
      "GW190517_055101"
    ],
    "T0": 35974486.145953126,
    "T0_days": 416.37136743001304,
    "pairs": [
      {
        "A": "GW190521",
        "B": "GW190519_153544",
        "lam": 0.5479958421950488,
        "t_pred_days": 303.8606556649341
      },
      {
        "A": "GW190521",
        "B": "GW190412",
        "lam": 0.47197181772982155,
        "t_pred_days": 251.1353073739019
      },
      {
        "A": "GW190521",
        "B": "GW190421_213856",
        "lam": 0.03224713755322206,
        "t_pred_days": 13.645618364032362
      },
      {
        "A": "GW190521",
        "B": "GW170104",
        "lam": 0.497627858633928,
        "t_pred_days": 268.4824640794445
      },
      {
        "A": "GW190521",
        "B": "GW170809",
        "lam": 0.27047640764764,
        "t_pred_days": 129.32023194127996
      },
      {
        "A": "GW190521",
        "B": "GW151226",
        "lam": 0.026580590188766573,
        "t_pred_days": 11.215797595489226
      },
      {
        "A": "GW190521",
        "B": "GW190517_055101",
        "lam": 0.3203020111759427,
        "t_pred_days": 157.19840125748132
      },
      {
        "A": "GW190519_153544",
        "B": "GW190412",
        "lam": 1.0199676599248704,
        "t_pred_days": 738.2701867931276
      },
      {
        "A": "GW190519_153544",
        "B": "GW190421_213856",
        "lam": 0.5157487046418268,
        "t_pred_days": 281.00571819645074
      },
      {
        "A": "GW190519_153544",
        "B": "GW170104",
        "lam": 0.05036798356112082,
        "t_pred_days": 21.508919611626467
      },
      {
        "A": "GW190519_153544",
        "B": "GW170809",
        "lam": 0.2775194345474088,
        "t_pred_days": 133.1771186900461
      },
      {
        "A": "GW190519_153544",
        "B": "GW151226",
        "lam": 0.5745764323838154,
        "t_pred_days": 323.2615492534694
      },
      {
        "A": "GW190519_153544",
        "B": "GW190517_055101",
        "lam": 0.8682978533709915,
        "t_pred_days": 575.779743818847
      },
      {
        "A": "GW190412",
        "B": "GW190421_213856",
        "lam": 0.5042189552830436,
        "t_pred_days": 273.0113105103315
      },
      {
        "A": "GW190412",
        "B": "GW170104",
        "lam": 0.9695996763637496,
        "t_pred_days": 681.5535610280875
      },
      {
        "A": "GW190412",
        "B": "GW170809",
        "lam": 0.7424482253774616,
        "t_pred_days": 458.4553220540767
      },
      {
        "A": "GW190412",
        "B": "GW151226",
        "lam": 0.445391227541055,
        "t_pred_days": 233.62631652804185
      },
      {
        "A": "GW190412",
        "B": "GW190517_055101",
        "lam": 0.15166980655387885,
        "t_pred_days": 68.19159618774998
      },
      {
        "A": "GW190421_213856",
        "B": "GW170104",
        "lam": 0.46538072108070594,
        "t_pred_days": 246.75017366150453
      },
      {
        "A": "GW190421_213856",
        "B": "GW170809",
        "lam": 0.23822927009441797,
        "t_pred_days": 112.00394082843196
      },
      {
        "A": "GW190421_213856",
        "B": "GW151226",
        "lam": 0.058827727741988634,
        "t_pred_days": 25.228988049266654
      },
      {
        "A": "GW190421_213856",
        "B": "GW190517_055101",
        "lam": 0.35254914872916476,
        "t_pred_days": 175.99583734672302
      },
      {
        "A": "GW170104",
        "B": "GW170809",
        "lam": 0.22715145098628797,
        "t_pred_days": 106.1829959573108
      },
      {
        "A": "GW170104",
        "B": "GW151226",
        "lam": 0.5242084488226946,
        "t_pred_days": 286.9303751452708
      },
      {
        "A": "GW170104",
        "B": "GW190517_055101",
        "lam": 0.8179298698098707,
        "t_pred_days": 527.0447376403016
      },
      {
        "A": "GW170809",
        "B": "GW151226",
        "lam": 0.2970569978364066,
        "t_pred_days": 144.01952926780893
      },
      {
        "A": "GW170809",
        "B": "GW190517_055101",
        "lam": 0.5907784188235827,
        "t_pred_days": 335.3426765927464
      },
      {
        "A": "GW151226",
        "B": "GW190517_055101",
        "lam": 0.29372142098717613,
        "t_pred_days": 142.15341637794958
      }
    ]
  }
}