{
  "event": "GW191204_171526",
  "gps": 1259514944.0,
  "distance_mpc": 640.0,
  "used": [
    "H1",
    "L1"
  ],
  "flow_Hz": 18.0,
  "fhigh_Hz": 380.0,
  "tau_band_Hz": [
    35.0,
    250.0
  ],
  "nu_band_Hz": [
    30.0,
    350.0
  ],
  "tau_hl_s": -0.002685546875,
  "TAU_SCALE": 1.0,
  "NU_SCALE": 1.0,
  "SCALE_EJ": 1.0,
  "PEAK_SCALE": 1.0,
  "E_internal": 7.151325010889098e+47,
  "energy_J": 7.151325010889098e+47,
  "msun_c2": 4.001529907025702,
  "nu_eff": {
    "nu_eff_energy": 194.15112588437515,
    "nu_eff_energy_raw": 201.32043852047977
  },
  "bw_all": {
    "f10": 73.87786229195208,
    "f50": 201.50919931422004,
    "f90": 332.05420862953935,
    "dnu_80": 258.17634633758723,
    "mu_f": 201.32043852047977,
    "sigma_f": 96.61539941028056
  },
  "bw_nu": {
    "f10": 73.7223538203026,
    "f50": 191.71824558610334,
    "f90": 319.48090935515876,
    "dnu_80": 245.75855553485616,
    "mu_f": 194.15112588437515,
    "sigma_f": 91.68344652886312
  },
  "freq_Hz": [
    18.0,
    18.5,
    19.0,
    19.5,
    20.0,
    20.5,
    21.0,
    21.5,
    22.0,
    22.5,
    23.0,
    23.5,
    24.0,
    24.5,
    25.0,
    25.5,
    26.0,
    26.5,
    27.0,
    27.5,
    28.0,
    28.5,
    29.0,
    29.5,
    30.0,
    30.5,
    31.0,
    31.5,
    32.0,
    32.5,
    33.0,
    33.5,
    34.0,
    34.5,
    35.0,
    35.5,
    36.0,
    36.5,
    37.0,
    37.5,
    38.0,
    38.5,
    39.0,
    39.5,
    40.0,
    40.5,
    41.0,
    41.5,
    42.0,
    42.5,
    43.0,
    43.5,
    44.0,
    44.5,
    45.0,
    45.5,
    46.0,
    46.5,
    47.0,
    47.5,
    48.0,
    48.5,
    49.0,
    49.5,
    50.0,
    50.5,
    51.0,
    51.5,
    52.0,
    52.5,
    53.0,
    53.5,
    54.0,
    54.5,
    55.0,
    55.5,
    56.0,
    56.5,
    57.0,
    57.5,
    58.0,
    58.5,
    59.0,
    59.5,
    60.0,
    60.5,
    61.0,
    61.5,
    62.0,
    62.5,
    63.0,
    63.5,
    64.0,
    64.5,
    65.0,
    65.5,
    66.0,
    66.5,
    67.0,
    67.5,
    68.0,
    68.5,
    69.0,
    69.5,
    70.0,
    70.5,
    71.0,
    71.5,
    72.0,
    72.5,
    73.0,
    73.5,
    74.0,
    74.5,
    75.0,
    75.5,
    76.0,
    76.5,
    77.0,
    77.5,
    78.0,
    78.5,
    79.0,
    79.5,
    80.0,
    80.5,
    81.0,
    81.5,
    82.0,
    82.5,
    83.0,
    83.5,
    84.0,
    84.5,
    85.0,
    85.5,
    86.0,
    86.5,
    87.0,
    87.5,
    88.0,
    88.5,
    89.0,
    89.5,
    90.0,
    90.5,
    91.0,
    91.5,
    92.0,
    92.5,
    93.0,
    93.5,
    94.0,
    94.5,
    95.0,
    95.5,
    96.0,
    96.5,
    97.0,
    97.5,
    98.0,
    98.5,
    99.0,
    99.5,
    100.0,
    100.5,
    101.0,
    101.5,
    102.0,
    102.5,
    103.0,
    103.5,
    104.0,
    104.5,
    105.0,
    105.5,
    106.0,
    106.5,
    107.0,
    107.5,
    108.0,
    108.5,
    109.0,
    109.5,
    110.0,
    110.5,
    111.0,
    111.5,
    112.0,
    112.5,
    113.0,
    113.5,
    114.0,
    114.5,
    115.0,
    115.5,
    116.0,
    116.5,
    117.0,
    117.5,
    118.0,
    118.5,
    119.0,
    119.5,
    120.0,
    120.5,
    121.0,
    121.5,
    122.0,
    122.5,
    123.0,
    123.5,
    124.0,
    124.5,
    125.0,
    125.5,
    126.0,
    126.5,
    127.0,
    127.5,
    128.0,
    128.5,
    129.0,
    129.5,
    130.0,
    130.5,
    131.0,
    131.5,
    132.0,
    132.5,
    133.0,
    133.5,
    134.0,
    134.5,
    135.0,
    135.5,
    136.0,
    136.5,
    137.0,
    137.5,
    138.0,
    138.5,
    139.0,
    139.5,
    140.0,
    140.5,
    141.0,
    141.5,
    142.0,
    142.5,
    143.0,
    143.5,
    144.0,
    144.5,
    145.0,
    145.5,
    146.0,
    146.5,
    147.0,
    147.5,
    148.0,
    148.5,
    149.0,
    149.5,
    150.0,
    150.5,
    151.0,
    151.5,
    152.0,
    152.5,
    153.0,
    153.5,
    154.0,
    154.5,
    155.0,
    155.5,
    156.0,
    156.5,
    157.0,
    157.5,
    158.0,
    158.5,
    159.0,
    159.5,
    160.0,
    160.5,
    161.0,
    161.5,
    162.0,
    162.5,
    163.0,
    163.5,
    164.0,
    164.5,
    165.0,
    165.5,
    166.0,
    166.5,
    167.0,
    167.5,
    168.0,
    168.5,
    169.0,
    169.5,
    170.0,
    170.5,
    171.0,
    171.5,
    172.0,
    172.5,
    173.0,
    173.5,
    174.0,
    174.5,
    175.0,
    175.5,
    176.0,
    176.5,
    177.0,
    177.5,
    178.0,
    178.5,
    179.0,
    179.5,
    180.0,
    180.5,
    181.0,
    181.5,
    182.0,
    182.5,
    183.0,
    183.5,
    184.0,
    184.5,
    185.0,
    185.5,
    186.0,
    186.5,
    187.0,
    187.5,
    188.0,
    188.5,
    189.0,
    189.5,
    190.0,
    190.5,
    191.0,
    191.5,
    192.0,
    192.5,
    193.0,
    193.5,
    194.0,
    194.5,
    195.0,
    195.5,
    196.0,
    196.5,
    197.0,
    197.5,
    198.0,
    198.5,
    199.0,
    199.5,
    200.0,
    200.5,
    201.0,
    201.5,
    202.0,
    202.5,
    203.0,
    203.5,
    204.0,
    204.5,
    205.0,
    205.5,
    206.0,
    206.5,
    207.0,
    207.5,
    208.0,
    208.5,
    209.0,
    209.5,
    210.0,
    210.5,
    211.0,
    211.5,
    212.0,
    212.5,
    213.0,
    213.5,
    214.0,
    214.5,
    215.0,
    215.5,
    216.0,
    216.5,
    217.0,
    217.5,
    218.0,
    218.5,
    219.0,
    219.5,
    220.0,
    220.5,
    221.0,
    221.5,
    222.0,
    222.5,
    223.0,
    223.5,
    224.0,
    224.5,
    225.0,
    225.5,
    226.0,
    226.5,
    227.0,
    227.5,
    228.0,
    228.5,
    229.0,
    229.5,
    230.0,
    230.5,
    231.0,
    231.5,
    232.0,
    232.5,
    233.0,
    233.5,
    234.0,
    234.5,
    235.0,
    235.5,
    236.0,
    236.5,
    237.0,
    237.5,
    238.0,
    238.5,
    239.0,
    239.5,
    240.0,
    240.5,
    241.0,
    241.5,
    242.0,
    242.5,
    243.0,
    243.5,
    244.0,
    244.5,
    245.0,
    245.5,
    246.0,
    246.5,
    247.0,
    247.5,
    248.0,
    248.5,
    249.0,
    249.5,
    250.0,
    250.5,
    251.0,
    251.5,
    252.0,
    252.5,
    253.0,
    253.5,
    254.0,
    254.5,
    255.0,
    255.5,
    256.0,
    256.5,
    257.0,
    257.5,
    258.0,
    258.5,
    259.0,
    259.5,
    260.0,
    260.5,
    261.0,
    261.5,
    262.0,
    262.5,
    263.0,
    263.5,
    264.0,
    264.5,
    265.0,
    265.5,
    266.0,
    266.5,
    267.0,
    267.5,
    268.0,
    268.5,
    269.0,
    269.5,
    270.0,
    270.5,
    271.0,
    271.5,
    272.0,
    272.5,
    273.0,
    273.5,
    274.0,
    274.5,
    275.0,
    275.5,
    276.0,
    276.5,
    277.0,
    277.5,
    278.0,
    278.5,
    279.0,
    279.5,
    280.0,
    280.5,
    281.0,
    281.5,
    282.0,
    282.5,
    283.0,
    283.5,
    284.0,
    284.5,
    285.0,
    285.5,
    286.0,
    286.5,
    287.0,
    287.5,
    288.0,
    288.5,
    289.0,
    289.5,
    290.0,
    290.5,
    291.0,
    291.5,
    292.0,
    292.5,
    293.0,
    293.5,
    294.0,
    294.5,
    295.0,
    295.5,
    296.0,
    296.5,
    297.0,
    297.5,
    298.0,
    298.5,
    299.0,
    299.5,
    300.0,
    300.5,
    301.0,
    301.5,
    302.0,
    302.5,
    303.0,
    303.5,
    304.0,
    304.5,
    305.0,
    305.5,
    306.0,
    306.5,
    307.0,
    307.5,
    308.0,
    308.5,
    309.0,
    309.5,
    310.0,
    310.5,
    311.0,
    311.5,
    312.0,
    312.5,
    313.0,
    313.5,
    314.0,
    314.5,
    315.0,
    315.5,
    316.0,
    316.5,
    317.0,
    317.5,
    318.0,
    318.5,
    319.0,
    319.5,
    320.0,
    320.5,
    321.0,
    321.5,
    322.0,
    322.5,
    323.0,
    323.5,
    324.0,
    324.5,
    325.0,
    325.5,
    326.0,
    326.5,
    327.0,
    327.5,
    328.0,
    328.5,
    329.0,
    329.5,
    330.0,
    330.5,
    331.0,
    331.5,
    332.0,
    332.5,
    333.0,
    333.5,
    334.0,
    334.5,
    335.0,
    335.5,
    336.0,
    336.5,
    337.0,
    337.5,
    338.0,
    338.5,
    339.0,
    339.5,
    340.0,
    340.5,
    341.0,
    341.5,
    342.0,
    342.5,
    343.0,
    343.5,
    344.0,
    344.5,
    345.0,
    345.5,
    346.0,
    346.5,
    347.0,
    347.5,
    348.0,
    348.5,
    349.0,
    349.5,
    350.0,
    350.5,
    351.0,
    351.5,
    352.0,
    352.5,
    353.0,
    353.5,
    354.0,
    354.5,
    355.0,
    355.5,
    356.0,
    356.5,
    357.0,
    357.5,
    358.0,
    358.5,
    359.0,
    359.5,
    360.0,
    360.5,
    361.0,
    361.5,
    362.0,
    362.5,
    363.0,
    363.5,
    364.0,
    364.5,
    365.0,
    365.5,
    366.0,
    366.5,
    367.0,
    367.5,
    368.0,
    368.5,
    369.0,
    369.5,
    370.0,
    370.5,
    371.0,
    371.5,
    372.0,
    372.5,
    373.0,
    373.5,
    374.0,
    374.5,
    375.0,
    375.5,
    376.0,
    376.5,
    377.0,
    377.5,
    378.0,
    378.5,
    379.0,
    379.5,
    380.0
  ],
  "dEdf_internal": [
    0.0,
    78.81868945612759,
    393.0315612434248,
    3379.2407731226817,
    4773.618954417782,
    86612.62563213315,
    287501.91553038853,
    257161.1837709096,
    99291.41332319446,
    189332.35930122988,
    988057.1933310973,
    1613753.3434613189,
    431592.394981528,
    355451.7284652047,
    322163.7221755713,
    17068607.296763804,
    507677.5278734663,
    6465475.702312,
    2437046.6786771063,
    8412802.943448348,
    853228.3778974381,
    9129394.613976082,
    50395849.04389461,
    23823048.212586887,
    17119969.02360406,
    19776090.58854736,
    2258756.022479572,
    10329495.490991455,
    33534900.705578048,
    1191852.512828932,
    15708124.253083285,
    32739437.03860371,
    106798535.79509024,
    56526051.03888419,
    19710820.07849113,
    1317100.374290347,
    1715150.692638783,
    7780009.746785945,
    19004972.374268632,
    17709069.57429775,
    9553152.97767639,
    2148585.9234375907,
    7303855.077978702,
    43801552.17467314,
    219274287.21607944,
    46078442.647788905,
    48197068.579405315,
    1674374.0173942132,
    27824708.18959938,
    42290844.54050812,
    23445977.524089456,
    8078438.263637562,
    24647553.46431005,
    53328650.571398154,
    5319738.62364222,
    4569485.19912733,
    41619730.87040449,
    19959347.369175944,
    4290861.292420271,
    19583123.54224546,
    61881447.45026574,
    29810696.222012725,
    83709255.55137815,
    38536687.79418796,
    7812416.698827538,
    83512092.13432832,
    67882804.56813693,
    36533797.98247493,
    19862250.16648545,
    51448036.95459636,
    5838240.548515445,
    2238688.5476975916,
    80855912.60289758,
    36431054.40434843,
    938282.4669841323,
    29717188.456250053,
    99696393.21967112,
    46909692.63018174,
    10498704.597406246,
    13467984.917259483,
    11725565.37734801,
    13792510.292298311,
    13555133.937162913,
    124563780.93636769,
    26829504.915758077,
    34274408.94130117,
    3643738.92425575,
    24510467.0126404,
    16243996.014138296,
    10870607.303345285,
    23692825.90426177,
    8346887.46488066,
    24440081.45041971,
    21182463.46490526,
    29422898.419924397,
    54934757.626227684,
    56963095.1996118,
    21612146.670583487,
    17612540.01516876,
    72052543.08241865,
    74387053.81691098,
    46567286.746430255,
    69796793.66594647,
    15052573.123906163,
    46056836.07473748,
    41602404.75239794,
    12108179.721479073,
    4426246.372503813,
    27070161.548946466,
    265917.63190391526,
    1358351.948877984,
    26764543.030003812,
    127217697.24831592,
    22535776.37298159,
    247424501.6813325,
    2194808.0558263357,
    70846167.12578337,
    49079222.7395558,
    294792.18081738683,
    57969065.27951891,
    14524329.192555591,
    25402994.619556535,
    17064963.885754995,
    41636177.859615,
    33871772.36469475,
    33251407.270191893,
    12813309.465005456,
    5894001.466747926,
    38888093.095359206,
    219090299.20344117,
    103352640.04490578,
    50326609.1497782,
    154837370.11905324,
    65334571.217256665,
    4646080.739950298,
    31295417.01073674,
    60669447.056808,
    81077593.1790533,
    40275380.57927941,
    157067999.25018278,
    78886579.24714364,
    93158858.49897873,
    29357627.831719026,
    219973055.9282629,
    67549336.48700194,
    32659050.34553049,
    149742282.16326305,
    2143078.108981149,
    176500988.24975505,
    6201238.653336793,
    21266780.40596983,
    93043297.68643412,
    8185452.174955306,
    266673253.45183983,
    2448101.792868357,
    16940767.991228607,
    9847292.659835499,
    11389280.669140479,
    47718096.74407622,
    25198487.489146408,
    44505717.82324154,
    56083930.50976449,
    136712773.90242633,
    29167042.91122555,
    4369885.609772553,
    7676315.237385177,
    66308817.83729845,
    165362721.40493435,
    15820649.352624787,
    8233193.835390165,
    9905569.080166584,
    25311178.42236199,
    47761946.805403754,
    27723405.820636008,
    26197036.867597926,
    9993133.70939808,
    73425172.71208215,
    62965607.885819584,
    25189735.72944356,
    113913307.25382511,
    29523162.384877365,
    17505156.16790967,
    6622941.459876347,
    49064136.4743811,
    16140731.662632829,
    106372951.6690272,
    79473231.89095476,
    8705552.534022754,
    153626543.70662186,
    31646647.49934845,
    45133908.80529588,
    8363448.74660466,
    49449779.13366828,
    17310944.945174076,
    23299415.085699026,
    10290497.356324837,
    11968433.08440886,
    14316226.445240391,
    28284528.396940317,
    28107096.26962179,
    5989110.612840418,
    18413655.338837545,
    35741414.75775071,
    106716899.30558379,
    58105357.934676446,
    25635078.54825688,
    81315480.12719819,
    39327445.74484953,
    64108934.72153078,
    46890549.47170261,
    57355334.89937045,
    57219056.25641564,
    9706946.342376022,
    5985780.494775028,
    5791541.558848489,
    89390763.99950977,
    172363939.3375761,
    62782296.638449706,
    1429901.5789111322,
    16524481.00570942,
    2995553.3472314076,
    88081845.1006885,
    32319001.275147054,
    36221120.36764516,
    4918070.408181588,
    32331411.54687639,
    19710224.765196968,
    21771674.27481383,
    40124338.895385824,
    3557929.6177561386,
    17342780.637510143,
    83994887.95882693,
    5647139.518896519,
    30280575.533822585,
    39147760.21990383,
    49759948.027791284,
    21159876.37624839,
    4188447.7253521113,
    67404868.75638624,
    29012010.764119044,
    3524941.500126705,
    15995672.807745634,
    20895596.891590755,
    64204205.18980689,
    24036327.94921389,
    70772565.90237351,
    21234259.96787091,
    86284432.00620997,
    17149402.290090423,
    96331611.38411734,
    1030060.7201249979,
    39527292.9532017,
    3198089.0879550055,
    32376647.43468998,
    79072253.3145434,
    54607715.03929946,
    29423993.319113083,
    1013930.4523819509,
    18591945.145986512,
    2702937.2988668,
    31297784.820300866,
    111207091.08566026,
    29913231.464117013,
    43868565.568464234,
    48813182.77006641,
    49334979.999172606,
    24980043.851810686,
    13945322.81635847,
    29625027.044762325,
    132180243.34283213,
    8659669.96921678,
    7919585.068464113,
    11175548.398392277,
    292963.443837812,
    3235950.088811093,
    92631354.89977406,
    72029467.00553262,
    60250271.99633134,
    1793334.1406023663,
    2275308.5279521537,
    61901439.11294197,
    73032920.52051596,
    25196304.222750813,
    83329537.0761359,
    3530197.2987691956,
    37577163.03691232,
    36185488.446133405,
    36682867.84176791,
    59658037.89724801,
    305928.6927665046,
    12235837.497185074,
    56390090.434565276,
    67373349.26187536,
    29308361.07493122,
    260260602.31564996,
    3281968.2360705095,
    2608261.39490601,
    4209467.6281483155,
    91225672.4800649,
    4149436.2422031523,
    123280173.17347601,
    18819089.323035985,
    11037514.25891686,
    44424912.54583448,
    86236465.54650779,
    6656279.648642108,
    85463328.92611639,
    87016414.31880598,
    129438997.32774831,
    47382520.710297145,
    41510373.932263754,
    17996499.768694796,
    5283914.988825426,
    33934023.64944436,
    181444125.34076637,
    52757018.115297824,
    9849738.595016195,
    32475392.84420701,
    1559878.1727916272,
    12292484.610696843,
    71078541.05166936,
    58919408.282516204,
    11306254.604358353,
    9785285.53523929,
    72785197.14942946,
    126110202.83183467,
    9093431.931944283,
    538238.773779341,
    58126366.44437009,
    68319387.36884592,
    44138824.68770164,
    3820627.214419714,
    23924089.209879577,
    68764760.32998677,
    96540531.0901077,
    10356963.969695484,
    11899395.669800473,
    89722561.76291648,
    424377.4854835212,
    48660257.56566387,
    66912007.28191358,
    77176720.27488253,
    56734111.3804058,
    102247758.37889522,
    8229345.037400955,
    101949519.79213805,
    4336785.995167436,
    151228008.91281146,
    57401313.403157525,
    30266192.64295351,
    448304.43763797294,
    41107649.20479917,
    23086238.023724284,
    61024358.52992263,
    28712250.383540045,
    25179838.504335154,
    19545679.094925486,
    4170710.508676367,
    10022057.731958505,
    33482251.927534357,
    43349372.8618135,
    11236239.955295613,
    54638095.92674664,
    140319888.04437995,
    14133185.678457014,
    4627277.196868291,
    8792488.1527418,
    13683352.824206071,
    33244045.223171424,
    108579913.71128893,
    84107364.80354786,
    10726331.463574508,
    79347286.83557463,
    1966854.1052663985,
    16408859.175930105,
    52035385.445021585,
    30070044.036690965,
    2088979.5064020553,
    16603709.635761518,
    75464672.3724171,
    7451060.980098871,
    160819018.44846904,
    10664769.758488711,
    6931611.785964626,
    43363379.21238808,
    10067050.110654432,
    69267806.431757,
    33430032.504228875,
    1177370.8805602887,
    109463567.86347294,
    22676727.837536067,
    125747445.33579285,
    1772463.5774773036,
    11428720.343671506,
    478626.54110004543,
    54546221.12121083,
    95384173.93815412,
    8426253.950426295,
    23374780.880414948,
    88918371.95371056,
    30872127.00896113,
    27918390.035069253,
    42931965.00848511,
    7194973.647791153,
    2433621.497583938,
    71769448.84955294,
    2361417.3223406156,
    259375.49133385633,
    16221520.210375352,
    10685667.15088767,
    9248471.029012756,
    35373397.90503173,
    46483601.12031845,
    37274148.919729896,
    62963261.327206135,
    29490452.198526632,
    24414942.028630614,
    39814893.96673755,
    106816193.73467705,
    15420369.211596258,
    4436999.811753765,
    94300864.63063633,
    52805751.305678956,
    17613663.44143483,
    87854509.96932897,
    5641632.384279595,
    10207322.75445503,
    70872841.99695697,
    22102465.551660445,
    65948557.87131161,
    59915153.013654865,
    27810525.521828197,
    30646321.339488424,
    40029953.90416404,
    76113846.05012281,
    38743750.3521071,
    26508658.287973378,
    43214792.44819733,
    36810262.608261175,
    81358795.79056224,
    14563312.61582738,
    73838112.9798913,
    18121757.847478256,
    17065595.792045437,
    62661524.536146045,
    25328162.793661695,
    3833135.2950512012,
    51434304.260300726,
    42719204.74848653,
    16534582.491264833,
    8503632.653309677,
    193928883.4195211,
    52945130.12758797,
    175194798.6310222,
    44363561.23923107,
    61816655.617059015,
    59097963.28710803,
    95479384.50530435,
    43946477.565698184,
    101769684.05333358,
    2108815.4927522847,
    34185002.00100631,
    4578429.47836697,
    186218900.13881037,
    142011111.09967682,
    177804923.35435218,
    21593199.49078013,
    52027108.12060135,
    14090376.543570388,
    14441966.771614717,
    9754391.75571748,
    54337149.7389109,
    28464196.393555313,
    4465651.168397665,
    16894611.17910695,
    3776702.4001440746,
    3797259.8752064463,
    12203684.516095852,
    6649090.88192809,
    50522732.408048645,
    14104642.610881602,
    20229687.743052192,
    16831377.51607596,
    31330011.529287625,
    68197001.93928944,
    19085655.934872642,
    59352947.27588938,
    332379228.3264375,
    47081366.59908092,
    4670095.125656461,
    52728950.03214283,
    23890590.540697493,
    52081858.00518525,
    24088982.53936372,
    24670427.907351617,
    51351540.1639303,
    10791091.180563565,
    12580197.632414185,
    57694126.574477956,
    82325897.35096118,
    19464948.136766672,
    6756627.762525245,
    12115138.814267013,
    4840406.345118052,
    25961747.190933958,
    9722264.249120837,
    55150991.69761545,
    45736165.96491408,
    76584568.44752355,
    14071865.970299456,
    36150882.56716098,
    104331343.3195803,
    44972709.59311968,
    53379744.94198284,
    28619412.382112645,
    16572762.871861715,
    3737883.9427094725,
    34514089.14810553,
    6962083.25855035,
    32395847.55278872,
    3750394.649741911,
    11193778.500938352,
    98192960.5282408,
    446638.5816836294,
    63577497.44927495,
    50153444.78751788,
    5253801.949380338,
    243286058.48843855,
    3789930.5208061286,
    16489931.994630672,
    28351421.889275894,
    46578459.16328565,
    7582587.785330543,
    27056319.38068003,
    6709925.9196915,
    22772010.418276165,
    111473915.51239522,
    48485815.25909022,
    24913839.87947743,
    10594071.49856991,
    1870556.4715403726,
    8408825.318236925,
    6788661.047132845,
    1109107.6381603694,
    43581263.8408289,
    14190121.009092888,
    28527945.959089004,
    3121984.812185155,
    56659981.496337466,
    40517223.614884645,
    5007015.772087738,
    2217040.4146516128,
    21974393.573944446,
    22716308.279351134,
    3641442.5442713513,
    41958520.41796527,
    29490688.25906136,
    60094249.253426075,
    24793446.680622015,
    106753261.52669726,
    13857093.739330335,
    20140500.769100565,
    164224671.94383648,
    17206338.545577303,
    28120423.77964613,
    14608988.995100252,
    5621600.533568051,
    32258240.853647232,
    32839849.586692624,
    171323688.43690214,
    134627623.75170428,
    140108704.76244354,
    5824556.665579754,
    12606033.236210857,
    33972994.36876132,
    40434402.948313296,
    135193306.26210612,
    589258638.6089755,
    7507261.024081043,
    1610937.9894783485,
    50431845.235918775,
    18974015.254852094,
    140835919.3302205,
    19386031.834819812,
    25407586.35465238,
    12423175.323085431,
    16065354.203237917,
    69130065.92996839,
    35817205.31866793,
    184862380.97491273,
    12944410.414990833,
    13577966.70790747,
    15985038.240346126,
    1952281.595801264,
    102040417.487756,
    65452129.031259544,
    15350691.221145134,
    105552324.69448146,
    9242414.463709457,
    83328851.87316155,
    32075582.908285838,
    18944302.768346734,
    19082557.14537899,
    38539279.54537791,
    95487521.32837714,
    9989416.350350259,
    3464361.438614425,
    9487130.69540725,
    97930454.66331035,
    28164746.09857197,
    8985773.882840078,
    41898645.719923064,
    106204483.05152097,
    44050011.78907525,
    22718424.50369346,
    8984623.064151222,
    84870036.7135085,
    40500420.72968523,
    6209163.063801036,
    146688070.65974444,
    28314259.71276944,
    155697800.06708765,
    9656145.42474465,
    22936570.691032674,
    38570940.330024764,
    80876543.55891426,
    140042339.3575055,
    2456748.8914112924,
    27064745.286423746,
    79273737.03124043,
    75196838.12166417,
    3213438.484292385,
    53208995.800443254,
    177129191.09352925,
    1734673.3801339525,
    30742763.43243662,
    82658213.65856057,
    130219043.04719335,
    115120411.03541173,
    18375107.74027294,
    37372688.36742933,
    26104548.325861424,
    34962180.88493318,
    94834143.02558695,
    28264198.627778478,
    11150168.779864103,
    7719539.637517459,
    20326469.74468756,
    29813774.685460366,
    47829124.87607259,
    72405150.70591906,
    35234247.3558704,
    25945506.076354533,
    19922110.215415858,
    2684663.4507263186,
    8516847.232035374,
    54112092.505706996,
    15816416.365304481,
    27870343.05101878,
    18157228.25816703,
    47903380.078774594,
    53132092.62767551,
    12543511.35513001,
    11521912.122008512,
    38361039.97846515,
    135857301.13456023,
    15238826.034294602,
    29955739.604256112,
    14256589.801865818,
    58296854.985954754,
    2281136.907111696,
    100830894.86117396,
    15025349.967316404,
    50308610.498828605,
    122264782.30386667,
    53330299.30053148,
    7528160.645191363,
    8388865.607376542,
    36513398.0163886,
    56599814.96141304,
    24024374.96795066,
    10553474.371557502,
    37896111.44439352,
    26392785.616927844,
    149888934.07060218,
    4956154.422699543,
    26076500.162774775,
    58954921.89028235,
    29168107.604422055,
    26964128.602477994,
    33803666.48213191,
    14603940.377272267,
    18341632.860524166,
    6364170.869982946,
    25804366.625206664,
    72702184.83561015,
    5566290.701085189,
    6242189.350593653,
    11455281.316725273,
    5127040.583661915,
    40674711.63970463,
    3984561.2532712948,
    17237566.26359173,
    3091119.769299609,
    3520771.318175127,
    7502258.78587998,
    4218584.05819931,
    6660471.986745338,
    5673685.644007215,
    1498443.2914941967,
    810690.1488302916,
    383982.3387035626,
    8706057.691573132,
    972707.9180594535,
    3301407.0297599696,
    395997.6826032018,
    139986.47308818222,
    11543.299415267145,
    484471.4535648076,
    22709.971603241425,
    48430.049955027534,
    2206.052145487089,
    3394.042710888307,
    186.0224545069351,
    0.0
  ]
}